{
  "game_date": "2026-05-20",
  "opponent": "Paddy Kelleys",
  "last_updated": "2026-05-20",
  "positions": {
    "P": {
      "number": "53",
      "name": "Mike Russo",
      "order": 12
    },
    "C": {
      "number": "17",
      "name": "Mike Stoico",
      "order": 10
    },
    "1B": {
      "number": "40",
      "name": "Chris Parello",
      "order": 9
    },
    "2B": {
      "number": "8",
      "name": "Brendan McCarthy",
      "order": 3
    },
    "SS": {
      "number": "10",
      "name": "Darren McDermott",
      "order": 7
    },
    "3B": {
      "number": "11",
      "name": "Eric Moody",
      "order": 8
    },
    "LF": {
      "number": "3",
      "name": "Jason Farrell",
      "order": 5
    },
    "LC": {
      "number": "69",
      "name": "Brendan Trohon",
      "order": 4
    },
    "RC": {
      "number": "24",
      "name": "Pat Hosman",
      "order": 2
    },
    "RF": {
      "number": "2",
      "name": "Tommy Dembowski",
      "order": 1
    },
    "EH1": {
      "number": "25",
      "name": "Joe Z.",
      "order": 6
    },
    "EH2": {
      "number": "33",
      "name": "Anthony Gagliano",
      "order": 11
    }
  },
  "bench": [
    {
      "number": "99",
      "name": "Assad Daaboul",
      "order": 0
    },
    {
      "number": "16",
      "name": "Thomas Evans",
      "order": 0
    },
    {
      "number": "7",
      "name": "Coach Barrows",
      "order": 0
    },
    {
      "number": "",
      "name": "",
      "order": 0
    },
    {
      "number": "",
      "name": "",
      "order": 0
    }
  ]
}